blackhc/project/__init__.py
blackhc/project/experiment.py
blackhc/project/script.py
blackhc/project/utils/__init__.py
blackhc/project/utils/component.py
blackhc/project/utils/config_class.py
blackhc/project/utils/context_stopwatch.py
blackhc/project/utils/cpu_memory.py
blackhc/project/utils/early_stopping.py
blackhc/project/utils/ignite_progress_bar.py
blackhc/project/utils/instrumentation.py
blackhc/project/utils/ipython_html_console.py
blackhc/project/utils/log_path.py
blackhc/project/utils/project_metadata.py
blackhc/project/utils/simple_storage.py
blackhc/project/utils/torch_cuda_memory.py
blackhc/project/utils/tree_namespace.py
blackhc/project/utils/wandb_log_path.py
blackhc/project/utils/tests/__init__.py
blackhc/project/utils/tests/test_component.py
blackhc/project/utils/tests/test_config_class.py
blackhc/project/utils/tests/test_cpu_mem_limit.py
blackhc/project/utils/tests/test_early_stopping.py
blackhc/project/utils/tests/test_instrumentation.py
blackhc/project/utils/tests/test_log_path.py
blackhc/project/utils/tests/test_simple_storage.py
blackhc/project/utils/tests/test_tree_namespace.py
blackhc/project/utils/tests/test_wandb_log_path.py
blackhc.project-7.0.0.dist-info/LICENSE
blackhc.project-7.0.0.dist-info/METADATA
blackhc.project-7.0.0.dist-info/WHEEL
blackhc.project-7.0.0.dist-info/top_level.txt
blackhc.project-7.0.0.dist-info/RECORD
