Metadata-Version: 2.1
Name: blackhc.project
Version: 7.0.0
Summary: Notebook setup code
Home-page: https://github.com/blackhc/notebook_setup
Author: Andreas @blackhc Kirsch
Author-email: blackhc+notebook_setup@gmail.com
License: MIT
Keywords: jupyter
Classifier: Development Status :: 5 - Production/Stable
Classifier: Intended Audience :: Developers
Classifier: Intended Audience :: Science/Research
Classifier: Topic :: Software Development :: Libraries :: Python Modules
Classifier: License :: OSI Approved :: Apache Software License
Classifier: Programming Language :: Python :: 3.10
License-File: LICENSE
Requires-Dist: gitpython
Requires-Dist: fs.sshfs
Requires-Dist: laaos
Requires-Dist: jsonpickle
Requires-Dist: toolz
Requires-Dist: jupyter-client<8.0.0
Requires-Dist: pyzmq<25
Provides-Extra: dev
Requires-Dist: check-manifest; extra == "dev"
Provides-Extra: test
Requires-Dist: coverage; extra == "test"
Requires-Dist: pytest; extra == "test"
Requires-Dist: pytest-forked; extra == "test"
Requires-Dist: pyfakefs==3.3; extra == "test"
Requires-Dist: torch; extra == "test"
Requires-Dist: psutil; extra == "test"
Requires-Dist: pytorch-ignite; extra == "test"
Requires-Dist: blackhc.progress-bar; extra == "test"
Requires-Dist: wandb; extra == "test"
Requires-Dist: prettyprinter; extra == "test"
Requires-Dist: rich; extra == "test"
Requires-Dist: markdownify; extra == "test"
Requires-Dist: ipython; extra == "test"
